azure_functions_validation/__init__.py
azure_functions_validation/adapter.py
azure_functions_validation/contract.py
azure_functions_validation/decorator.py
azure_functions_validation/exceptions.py
azure_functions_validation/openapi.py
azure_functions_validation/registry.py
azure_functions_validation-0.3.0.dist-info/METADATA
azure_functions_validation-0.3.0.dist-info/WHEEL
azure_functions_validation-0.3.0.dist-info/licenses/LICENSE
azure_functions_validation-0.3.0.dist-info/RECORD
