Metadata-Version: 2.4
Name: azure-functions-validation
Version: 0.3.0
Summary: Validation and serialization layer for Python-based Azure Functions
Author-email: Yeongseon Choe <yeongseon.choe@gmail.com>
License-Expression: MIT
License-File: LICENSE
Requires-Python: <3.15,>=3.10
Requires-Dist: azure-functions
Requires-Dist: pydantic<3.0,>=2.0
Provides-Extra: dev
Requires-Dist: bandit==1.9.3; extra == 'dev'
Requires-Dist: black==26.1.0; extra == 'dev'
Requires-Dist: build; extra == 'dev'
Requires-Dist: coverage; extra == 'dev'
Requires-Dist: git-changelog; extra == 'dev'
Requires-Dist: hatch; extra == 'dev'
Requires-Dist: mypy==1.19.1; extra == 'dev'
Requires-Dist: pre-commit; extra == 'dev'
Requires-Dist: pytest; extra == 'dev'
Requires-Dist: pytest-cov; extra == 'dev'
Requires-Dist: ruff==0.14.14; extra == 'dev'
Provides-Extra: docs
Requires-Dist: mkdocs; extra == 'docs'
Requires-Dist: mkdocs-material; extra == 'docs'
